proton/__init__.py
proton/__main__.py
proton/document.py
proton/js.py
proton/runpython.js
proton/utils.py
proton/window.py
proton_web-0.1.1.dist-info/METADATA
proton_web-0.1.1.dist-info/WHEEL
proton_web-0.1.1.dist-info/licenses/LICENSE
proton_web-0.1.1.dist-info/RECORD
